pyarrow-stubs/__init__.pyi
pyarrow-stubs/_azurefs.pyi
pyarrow-stubs/_compute.pyi
pyarrow-stubs/_csv.pyi
pyarrow-stubs/_cuda.pyi
pyarrow-stubs/_dataset.pyi
pyarrow-stubs/_dataset_orc.pyi
pyarrow-stubs/_dataset_parquet.pyi
pyarrow-stubs/_dataset_parquet_encryption.pyi
pyarrow-stubs/_feather.pyi
pyarrow-stubs/_flight.pyi
pyarrow-stubs/_fs.pyi
pyarrow-stubs/_gcsfs.pyi
pyarrow-stubs/_hdfs.pyi
pyarrow-stubs/_json.pyi
pyarrow-stubs/_orc.pyi
pyarrow-stubs/_parquet.pyi
pyarrow-stubs/_parquet_encryption.pyi
pyarrow-stubs/_s3fs.pyi
pyarrow-stubs/_stubs_typing.pyi
pyarrow-stubs/_substrait.pyi
pyarrow-stubs/acero.pyi
pyarrow-stubs/cffi.pyi
pyarrow-stubs/compute.pyi
pyarrow-stubs/dataset.pyi
pyarrow-stubs/feather.pyi
pyarrow-stubs/flight.pyi
pyarrow-stubs/fs.pyi
pyarrow-stubs/gandiva.pyi
pyarrow-stubs/ipc.pyi
pyarrow-stubs/json.pyi
pyarrow-stubs/lib.pyi
pyarrow-stubs/orc.pyi
pyarrow-stubs/pandas_compat.pyi
pyarrow-stubs/substrait.pyi
pyarrow-stubs/types.pyi
pyarrow-stubs/util.pyi
pyarrow-stubs/__lib_pxi/__init__.pyi
pyarrow-stubs/__lib_pxi/array.pyi
pyarrow-stubs/__lib_pxi/benchmark.pyi
pyarrow-stubs/__lib_pxi/builder.pyi
pyarrow-stubs/__lib_pxi/compat.pyi
pyarrow-stubs/__lib_pxi/config.pyi
pyarrow-stubs/__lib_pxi/device.pyi
pyarrow-stubs/__lib_pxi/error.pyi
pyarrow-stubs/__lib_pxi/io.pyi
pyarrow-stubs/__lib_pxi/ipc.pyi
pyarrow-stubs/__lib_pxi/memory.pyi
pyarrow-stubs/__lib_pxi/pandas_shim.pyi
pyarrow-stubs/__lib_pxi/scalar.pyi
pyarrow-stubs/__lib_pxi/table.pyi
pyarrow-stubs/__lib_pxi/tensor.pyi
pyarrow-stubs/__lib_pxi/types.pyi
pyarrow-stubs/interchange/__init__.pyi
pyarrow-stubs/interchange/buffer.pyi
pyarrow-stubs/interchange/column.pyi
pyarrow-stubs/interchange/dataframe.pyi
pyarrow-stubs/interchange/from_dataframe.pyi
pyarrow-stubs/parquet/__init__.pyi
pyarrow-stubs/parquet/core.pyi
pyarrow-stubs/parquet/encryption.pyi
pyarrow_stubs-20240830.dist-info/METADATA
pyarrow_stubs-20240830.dist-info/WHEEL
pyarrow_stubs-20240830.dist-info/licenses/LICENSE
pyarrow_stubs-20240830.dist-info/RECORD
